bumgr/__init__.py
bumgr/__main__.py
bumgr/backup.py
bumgr/cli.py
bumgr/config.py
bumgr/executable.py
bumgr/contrib/__init__.py
bumgr/contrib/power.py
bumgr/contrib/tailscale.py
bumgr-0.5.1.dist-info/METADATA
bumgr-0.5.1.dist-info/WHEEL
bumgr-0.5.1.dist-info/entry_points.txt
bumgr-0.5.1.dist-info/licenses/LICENSE
bumgr-0.5.1.dist-info/RECORD
