Metadata-Version: 2.4
Name: bumgr
Version: 0.5.1
Summary: Backup management for restic
Project-URL: Release notes, https://github.com/3j14/bumgr/blob/main/CHANGELOG.md
Project-URL: Source, https://github.com/3j14/bumgr
Project-URL: Tracker, https://github.com/3j14/bumgr/issues
Author-email: Jonas Drotleff <jonas.drotleff@3j14.de>
License: BSD-3-Clause
License-File: LICENSE
Classifier: Development Status :: 3 - Alpha
Classifier: License :: OSI Approved :: BSD License
Classifier: Operating System :: POSIX
Classifier: Operating System :: Unix
Classifier: Programming Language :: Python :: 3
Classifier: Programming Language :: Python :: 3.11
Classifier: Programming Language :: Python :: 3.12
Classifier: Programming Language :: Python :: 3.13
Classifier: Topic :: System :: Archiving :: Backup
Classifier: Topic :: System :: Filesystems
Classifier: Topic :: System :: Networking
Requires-Python: >=3.11
Requires-Dist: rich>=13.9.3
Provides-Extra: dev
Requires-Dist: mypy>=1.13.0; extra == 'dev'
Requires-Dist: pre-commit>=4.0.1; extra == 'dev'
Requires-Dist: ruff>=0.6.9; extra == 'dev'
Provides-Extra: test
Requires-Dist: pytest>=8.3.3; extra == 'test'
